{
    "description": "",
    "tags": [
        {
            "id": 131555885,
            "tagId": 30423921,
            "name": "bad quality",
            "value": null,
            "labelerLogin": "akoublis",
            "createdAt": "2022-09-24T08:16:13.486Z",
            "updatedAt": "2022-09-24T08:16:13.486Z"
        }
    ],
    "size": {
        "height": 64,
        "width": 48
    },
    "objects": [
        {
            "id": 1037252714,
            "classId": 10353148,
            "description": "",
            "geometryType": "point",
            "labelerLogin": "akoublis",
            "createdAt": "2022-09-24T08:16:10.728Z",
            "updatedAt": "2022-09-24T08:16:10.728Z",
            "tags": [],
            "classTitle": "Top",
            "points": {
                "exterior": [
                    [
                        39,
                        59
                    ]
                ],
                "interior": []
            }
        },
        {
            "id": 1037252712,
            "classId": 10353148,
            "description": "",
            "geometryType": "point",
            "labelerLogin": "akoublis",
            "createdAt": "2022-09-24T08:16:07.662Z",
            "updatedAt": "2022-09-24T08:16:07.662Z",
            "tags": [],
            "classTitle": "Top",
            "points": {
                "exterior": [
                    [
                        36,
                        48
                    ]
                ],
                "interior": []
            }
        },
        {
            "id": 1037252711,
            "classId": 10353148,
            "description": "",
            "geometryType": "point",
            "labelerLogin": "akoublis",
            "createdAt": "2022-09-24T08:16:05.521Z",
            "updatedAt": "2022-09-24T08:16:05.521Z",
            "tags": [],
            "classTitle": "Top",
            "points": {
                "exterior": [
                    [
                        35,
                        39
                    ]
                ],
                "interior": []
            }
        },
        {
            "id": 1037252710,
            "classId": 10353148,
            "description": "",
            "geometryType": "point",
            "labelerLogin": "akoublis",
            "createdAt": "2022-09-24T08:16:03.913Z",
            "updatedAt": "2022-09-24T08:16:03.913Z",
            "tags": [],
            "classTitle": "Top",
            "points": {
                "exterior": [
                    [
                        30,
                        27
                    ]
                ],
                "interior": []
            }
        },
        {
            "id": 1037252708,
            "classId": 10353148,
            "description": "",
            "geometryType": "point",
            "labelerLogin": "akoublis",
            "createdAt": "2022-09-24T08:16:01.756Z",
            "updatedAt": "2022-09-24T08:16:01.756Z",
            "tags": [],
            "classTitle": "Top",
            "points": {
                "exterior": [
                    [
                        26,
                        39
                    ]
                ],
                "interior": []
            }
        },
        {
            "id": 1037252706,
            "classId": 10353148,
            "description": "",
            "geometryType": "point",
            "labelerLogin": "akoublis",
            "createdAt": "2022-09-24T08:16:00.420Z",
            "updatedAt": "2022-09-24T08:16:00.420Z",
            "tags": [],
            "classTitle": "Top",
            "points": {
                "exterior": [
                    [
                        24,
                        48
                    ]
                ],
                "interior": []
            }
        },
        {
            "id": 1037252704,
            "classId": 10353148,
            "description": "",
            "geometryType": "point",
            "labelerLogin": "akoublis",
            "createdAt": "2022-09-24T08:15:58.981Z",
            "updatedAt": "2022-09-24T08:15:58.981Z",
            "tags": [],
            "classTitle": "Top",
            "points": {
                "exterior": [
                    [
                        21,
                        59
                    ]
                ],
                "interior": []
            }
        }
    ]
}