{
    "description": "",
    "tags": [
        {
            "id": 130542745,
            "tagId": 30423921,
            "name": "bad quality",
            "value": null,
            "labelerLogin": "Peter",
            "createdAt": "2022-09-14T18:53:35.554Z",
            "updatedAt": "2022-09-14T18:53:35.554Z"
        }
    ],
    "size": {
        "height": 64,
        "width": 48
    },
    "objects": [
        {
            "id": 1025821407,
            "classId": 10353148,
            "description": "",
            "geometryType": "point",
            "labelerLogin": "Peter",
            "createdAt": "2022-09-14T18:53:34.706Z",
            "updatedAt": "2022-09-14T18:53:34.706Z",
            "tags": [],
            "classTitle": "Top",
            "points": {
                "exterior": [
                    [
                        34,
                        50
                    ]
                ],
                "interior": []
            }
        },
        {
            "id": 1025821406,
            "classId": 10353148,
            "description": "",
            "geometryType": "point",
            "labelerLogin": "Peter",
            "createdAt": "2022-09-14T18:53:33.370Z",
            "updatedAt": "2022-09-14T18:53:33.370Z",
            "tags": [],
            "classTitle": "Top",
            "points": {
                "exterior": [
                    [
                        32,
                        36
                    ]
                ],
                "interior": []
            }
        },
        {
            "id": 1025821405,
            "classId": 10353148,
            "description": "",
            "geometryType": "point",
            "labelerLogin": "Peter",
            "createdAt": "2022-09-14T18:53:31.340Z",
            "updatedAt": "2022-09-14T18:53:31.340Z",
            "tags": [],
            "classTitle": "Top",
            "points": {
                "exterior": [
                    [
                        30,
                        21
                    ]
                ],
                "interior": []
            }
        },
        {
            "id": 1025821403,
            "classId": 10353148,
            "description": "",
            "geometryType": "point",
            "labelerLogin": "Peter",
            "createdAt": "2022-09-14T18:53:29.911Z",
            "updatedAt": "2022-09-14T18:53:29.911Z",
            "tags": [],
            "classTitle": "Top",
            "points": {
                "exterior": [
                    [
                        24,
                        6
                    ]
                ],
                "interior": []
            }
        },
        {
            "id": 1025821367,
            "classId": 10353148,
            "description": "",
            "geometryType": "point",
            "labelerLogin": "Peter",
            "createdAt": "2022-09-14T18:53:27.881Z",
            "updatedAt": "2022-09-14T18:53:27.881Z",
            "tags": [],
            "classTitle": "Top",
            "points": {
                "exterior": [
                    [
                        19,
                        21
                    ]
                ],
                "interior": []
            }
        },
        {
            "id": 1025821365,
            "classId": 10353148,
            "description": "",
            "geometryType": "point",
            "labelerLogin": "Peter",
            "createdAt": "2022-09-14T18:53:25.674Z",
            "updatedAt": "2022-09-14T18:53:25.674Z",
            "tags": [],
            "classTitle": "Top",
            "points": {
                "exterior": [
                    [
                        17,
                        36
                    ]
                ],
                "interior": []
            }
        },
        {
            "id": 1025821363,
            "classId": 10353148,
            "description": "",
            "geometryType": "point",
            "labelerLogin": "Peter",
            "createdAt": "2022-09-14T18:53:24.168Z",
            "updatedAt": "2022-09-14T18:53:24.168Z",
            "tags": [],
            "classTitle": "Top",
            "points": {
                "exterior": [
                    [
                        15,
                        51
                    ]
                ],
                "interior": []
            }
        }
    ]
}