{
    "description": "",
    "tags": [
        {
            "id": 130477668,
            "tagId": 30423921,
            "name": "bad quality",
            "value": null,
            "labelerLogin": "aioannides",
            "createdAt": "2022-09-13T10:08:12.002Z",
            "updatedAt": "2022-09-13T10:08:12.002Z"
        }
    ],
    "size": {
        "height": 64,
        "width": 48
    },
    "objects": [
        {
            "id": 1024302699,
            "classId": 10353148,
            "description": "",
            "geometryType": "point",
            "labelerLogin": "aioannides",
            "createdAt": "2022-09-13T10:08:48.582Z",
            "updatedAt": "2022-09-13T10:09:53.981Z",
            "tags": [],
            "classTitle": "Top",
            "points": {
                "exterior": [
                    [
                        33,
                        50
                    ]
                ],
                "interior": []
            }
        },
        {
            "id": 1024302693,
            "classId": 10353148,
            "description": "",
            "geometryType": "point",
            "labelerLogin": "aioannides",
            "createdAt": "2022-09-13T10:08:45.928Z",
            "updatedAt": "2022-09-13T10:10:09.487Z",
            "tags": [],
            "classTitle": "Top",
            "points": {
                "exterior": [
                    [
                        31,
                        37
                    ]
                ],
                "interior": []
            }
        },
        {
            "id": 1024302692,
            "classId": 10353148,
            "description": "",
            "geometryType": "point",
            "labelerLogin": "aioannides",
            "createdAt": "2022-09-13T10:08:43.548Z",
            "updatedAt": "2022-09-13T10:09:26.259Z",
            "tags": [],
            "classTitle": "Top",
            "points": {
                "exterior": [
                    [
                        28,
                        22
                    ]
                ],
                "interior": []
            }
        },
        {
            "id": 1024302688,
            "classId": 10353148,
            "description": "",
            "geometryType": "point",
            "labelerLogin": "aioannides",
            "createdAt": "2022-09-13T10:08:41.668Z",
            "updatedAt": "2022-09-13T10:08:41.668Z",
            "tags": [],
            "classTitle": "Top",
            "points": {
                "exterior": [
                    [
                        24,
                        8
                    ]
                ],
                "interior": []
            }
        },
        {
            "id": 1024302683,
            "classId": 10353148,
            "description": "",
            "geometryType": "point",
            "labelerLogin": "aioannides",
            "createdAt": "2022-09-13T10:08:40.344Z",
            "updatedAt": "2022-09-13T10:09:17.267Z",
            "tags": [],
            "classTitle": "Top",
            "points": {
                "exterior": [
                    [
                        19,
                        22
                    ]
                ],
                "interior": []
            }
        },
        {
            "id": 1024302638,
            "classId": 10353148,
            "description": "",
            "geometryType": "point",
            "labelerLogin": "aioannides",
            "createdAt": "2022-09-13T10:08:15.965Z",
            "updatedAt": "2022-09-13T10:08:26.645Z",
            "tags": [],
            "classTitle": "Top",
            "points": {
                "exterior": [
                    [
                        17,
                        37
                    ]
                ],
                "interior": []
            }
        },
        {
            "id": 1024302636,
            "classId": 10353148,
            "description": "",
            "geometryType": "point",
            "labelerLogin": "aioannides",
            "createdAt": "2022-09-13T10:08:15.534Z",
            "updatedAt": "2022-09-13T10:10:22.426Z",
            "tags": [
                {
                    "id": 154700012,
                    "tagId": 30423921,
                    "name": "bad quality",
                    "value": null,
                    "labelerLogin": "aioannides",
                    "createdAt": "2022-09-13T10:10:25.422Z",
                    "updatedAt": "2022-09-13T10:10:25.422Z"
                }
            ],
            "classTitle": "Top",
            "points": {
                "exterior": [
                    [
                        16,
                        50
                    ]
                ],
                "interior": []
            }
        }
    ]
}