{
    "description": "",
    "tags": [],
    "size": {
        "height": 64,
        "width": 48
    },
    "objects": [
        {
            "id": 1026417937,
            "classId": 10353148,
            "description": "",
            "geometryType": "point",
            "labelerLogin": "Peter",
            "createdAt": "2022-09-16T06:35:31.394Z",
            "updatedAt": "2022-09-16T06:35:31.394Z",
            "tags": [],
            "classTitle": "Top",
            "points": {
                "exterior": [
                    [
                        35,
                        52
                    ]
                ],
                "interior": []
            }
        },
        {
            "id": 1026417927,
            "classId": 10353148,
            "description": "",
            "geometryType": "point",
            "labelerLogin": "Peter",
            "createdAt": "2022-09-16T06:35:30.042Z",
            "updatedAt": "2022-09-16T06:35:30.042Z",
            "tags": [],
            "classTitle": "Top",
            "points": {
                "exterior": [
                    [
                        33,
                        35
                    ]
                ],
                "interior": []
            }
        },
        {
            "id": 1026417922,
            "classId": 10353148,
            "description": "",
            "geometryType": "point",
            "labelerLogin": "Peter",
            "createdAt": "2022-09-16T06:35:28.718Z",
            "updatedAt": "2022-09-16T06:35:28.718Z",
            "tags": [],
            "classTitle": "Top",
            "points": {
                "exterior": [
                    [
                        32,
                        20
                    ]
                ],
                "interior": []
            }
        },
        {
            "id": 1026417916,
            "classId": 10353148,
            "description": "",
            "geometryType": "point",
            "labelerLogin": "Peter",
            "createdAt": "2022-09-16T06:35:27.527Z",
            "updatedAt": "2022-09-16T06:35:27.527Z",
            "tags": [],
            "classTitle": "Top",
            "points": {
                "exterior": [
                    [
                        27,
                        2
                    ]
                ],
                "interior": []
            }
        },
        {
            "id": 1026417909,
            "classId": 10353148,
            "description": "",
            "geometryType": "point",
            "labelerLogin": "Peter",
            "createdAt": "2022-09-16T06:35:26.528Z",
            "updatedAt": "2022-09-16T06:35:26.528Z",
            "tags": [],
            "classTitle": "Top",
            "points": {
                "exterior": [
                    [
                        20,
                        19
                    ]
                ],
                "interior": []
            }
        },
        {
            "id": 1026417902,
            "classId": 10353148,
            "description": "",
            "geometryType": "point",
            "labelerLogin": "Peter",
            "createdAt": "2022-09-16T06:35:25.328Z",
            "updatedAt": "2022-09-16T06:35:25.328Z",
            "tags": [],
            "classTitle": "Top",
            "points": {
                "exterior": [
                    [
                        17,
                        33
                    ]
                ],
                "interior": []
            }
        },
        {
            "id": 1026417896,
            "classId": 10353148,
            "description": "",
            "geometryType": "point",
            "labelerLogin": "Peter",
            "createdAt": "2022-09-16T06:35:24.174Z",
            "updatedAt": "2022-09-16T06:35:24.174Z",
            "tags": [],
            "classTitle": "Top",
            "points": {
                "exterior": [
                    [
                        14,
                        50
                    ]
                ],
                "interior": []
            }
        }
    ]
}