{
    "description": "",
    "tags": [],
    "size": {
        "height": 64,
        "width": 48
    },
    "objects": [
        {
            "id": 1027306925,
            "classId": 10353148,
            "description": "",
            "geometryType": "point",
            "labelerLogin": "aioannides",
            "createdAt": "2022-09-17T09:21:43.845Z",
            "updatedAt": "2022-09-17T09:21:43.845Z",
            "tags": [],
            "classTitle": "Top",
            "points": {
                "exterior": [
                    [
                        35,
                        52
                    ]
                ],
                "interior": []
            }
        },
        {
            "id": 1027306923,
            "classId": 10353148,
            "description": "",
            "geometryType": "point",
            "labelerLogin": "aioannides",
            "createdAt": "2022-09-17T09:21:41.800Z",
            "updatedAt": "2022-09-17T09:21:41.800Z",
            "tags": [],
            "classTitle": "Top",
            "points": {
                "exterior": [
                    [
                        32,
                        35
                    ]
                ],
                "interior": []
            }
        },
        {
            "id": 1027306922,
            "classId": 10353148,
            "description": "",
            "geometryType": "point",
            "labelerLogin": "aioannides",
            "createdAt": "2022-09-17T09:21:39.853Z",
            "updatedAt": "2022-09-17T09:21:39.853Z",
            "tags": [],
            "classTitle": "Top",
            "points": {
                "exterior": [
                    [
                        30,
                        23
                    ]
                ],
                "interior": []
            }
        },
        {
            "id": 1027306921,
            "classId": 10353148,
            "description": "",
            "geometryType": "point",
            "labelerLogin": "aioannides",
            "createdAt": "2022-09-17T09:21:37.487Z",
            "updatedAt": "2022-09-17T09:22:06.953Z",
            "tags": [],
            "classTitle": "Top",
            "points": {
                "exterior": [
                    [
                        25,
                        7
                    ]
                ],
                "interior": []
            }
        },
        {
            "id": 1027306920,
            "classId": 10353148,
            "description": "",
            "geometryType": "point",
            "labelerLogin": "aioannides",
            "createdAt": "2022-09-17T09:21:36.040Z",
            "updatedAt": "2022-09-17T09:21:36.040Z",
            "tags": [],
            "classTitle": "Top",
            "points": {
                "exterior": [
                    [
                        20,
                        23
                    ]
                ],
                "interior": []
            }
        },
        {
            "id": 1027306918,
            "classId": 10353148,
            "description": "",
            "geometryType": "point",
            "labelerLogin": "aioannides",
            "createdAt": "2022-09-17T09:21:34.111Z",
            "updatedAt": "2022-09-17T09:21:59.985Z",
            "tags": [],
            "classTitle": "Top",
            "points": {
                "exterior": [
                    [
                        18,
                        35
                    ]
                ],
                "interior": []
            }
        },
        {
            "id": 1027306917,
            "classId": 10353148,
            "description": "",
            "geometryType": "point",
            "labelerLogin": "aioannides",
            "createdAt": "2022-09-17T09:21:32.971Z",
            "updatedAt": "2022-09-17T09:21:32.971Z",
            "tags": [],
            "classTitle": "Top",
            "points": {
                "exterior": [
                    [
                        14,
                        52
                    ]
                ],
                "interior": []
            }
        }
    ]
}