{
    "description": "",
    "tags": [],
    "size": {
        "height": 64,
        "width": 48
    },
    "objects": [
        {
            "id": 1025820094,
            "classId": 10353148,
            "description": "",
            "geometryType": "point",
            "labelerLogin": "Peter",
            "createdAt": "2022-09-14T18:31:34.414Z",
            "updatedAt": "2022-09-14T18:31:34.414Z",
            "tags": [],
            "classTitle": "Top",
            "points": {
                "exterior": [
                    [
                        32,
                        51
                    ]
                ],
                "interior": []
            }
        },
        {
            "id": 1025820093,
            "classId": 10353148,
            "description": "",
            "geometryType": "point",
            "labelerLogin": "Peter",
            "createdAt": "2022-09-14T18:31:33.425Z",
            "updatedAt": "2022-09-14T18:31:33.425Z",
            "tags": [],
            "classTitle": "Top",
            "points": {
                "exterior": [
                    [
                        29,
                        36
                    ]
                ],
                "interior": []
            }
        },
        {
            "id": 1025820092,
            "classId": 10353148,
            "description": "",
            "geometryType": "point",
            "labelerLogin": "Peter",
            "createdAt": "2022-09-14T18:31:32.334Z",
            "updatedAt": "2022-09-14T18:31:32.334Z",
            "tags": [],
            "classTitle": "Top",
            "points": {
                "exterior": [
                    [
                        26,
                        22
                    ]
                ],
                "interior": []
            }
        },
        {
            "id": 1025820090,
            "classId": 10353148,
            "description": "",
            "geometryType": "point",
            "labelerLogin": "Peter",
            "createdAt": "2022-09-14T18:31:31.173Z",
            "updatedAt": "2022-09-14T18:31:31.173Z",
            "tags": [],
            "classTitle": "Top",
            "points": {
                "exterior": [
                    [
                        20,
                        6
                    ]
                ],
                "interior": []
            }
        },
        {
            "id": 1025820089,
            "classId": 10353148,
            "description": "",
            "geometryType": "point",
            "labelerLogin": "Peter",
            "createdAt": "2022-09-14T18:31:30.340Z",
            "updatedAt": "2022-09-14T18:31:30.340Z",
            "tags": [],
            "classTitle": "Top",
            "points": {
                "exterior": [
                    [
                        14,
                        21
                    ]
                ],
                "interior": []
            }
        },
        {
            "id": 1025820087,
            "classId": 10353148,
            "description": "",
            "geometryType": "point",
            "labelerLogin": "Peter",
            "createdAt": "2022-09-14T18:31:29.269Z",
            "updatedAt": "2022-09-14T18:31:29.269Z",
            "tags": [],
            "classTitle": "Top",
            "points": {
                "exterior": [
                    [
                        13,
                        37
                    ]
                ],
                "interior": []
            }
        },
        {
            "id": 1025820086,
            "classId": 10353148,
            "description": "",
            "geometryType": "point",
            "labelerLogin": "Peter",
            "createdAt": "2022-09-14T18:31:27.944Z",
            "updatedAt": "2022-09-14T18:31:27.944Z",
            "tags": [],
            "classTitle": "Top",
            "points": {
                "exterior": [
                    [
                        12,
                        52
                    ]
                ],
                "interior": []
            }
        }
    ]
}