{
    "description": "",
    "tags": [
        {
            "id": 131557124,
            "tagId": 30434435,
            "name": "bad quality",
            "value": null,
            "labelerLogin": "Peter",
            "createdAt": "2022-09-25T13:44:48.362Z",
            "updatedAt": "2022-09-25T13:44:48.362Z"
        }
    ],
    "size": {
        "height": 64,
        "width": 48
    },
    "objects": [
        {
            "id": 1037300802,
            "classId": 10374605,
            "description": "",
            "geometryType": "point",
            "labelerLogin": "Peter",
            "createdAt": "2022-09-25T13:44:46.922Z",
            "updatedAt": "2022-09-25T13:44:46.922Z",
            "tags": [],
            "classTitle": "Top",
            "points": {
                "exterior": [
                    [
                        34,
                        50
                    ]
                ],
                "interior": []
            }
        },
        {
            "id": 1037300799,
            "classId": 10374605,
            "description": "",
            "geometryType": "point",
            "labelerLogin": "Peter",
            "createdAt": "2022-09-25T13:44:45.343Z",
            "updatedAt": "2022-09-25T13:44:45.343Z",
            "tags": [],
            "classTitle": "Top",
            "points": {
                "exterior": [
                    [
                        30,
                        38
                    ]
                ],
                "interior": []
            }
        },
        {
            "id": 1037300797,
            "classId": 10374605,
            "description": "",
            "geometryType": "point",
            "labelerLogin": "Peter",
            "createdAt": "2022-09-25T13:44:43.066Z",
            "updatedAt": "2022-09-25T13:44:43.066Z",
            "tags": [],
            "classTitle": "Top",
            "points": {
                "exterior": [
                    [
                        27,
                        26
                    ]
                ],
                "interior": []
            }
        },
        {
            "id": 1037300796,
            "classId": 10374605,
            "description": "",
            "geometryType": "point",
            "labelerLogin": "Peter",
            "createdAt": "2022-09-25T13:44:41.589Z",
            "updatedAt": "2022-09-25T13:44:41.589Z",
            "tags": [],
            "classTitle": "Top",
            "points": {
                "exterior": [
                    [
                        20,
                        14
                    ]
                ],
                "interior": []
            }
        },
        {
            "id": 1037300794,
            "classId": 10374605,
            "description": "",
            "geometryType": "point",
            "labelerLogin": "Peter",
            "createdAt": "2022-09-25T13:44:40.397Z",
            "updatedAt": "2022-09-25T13:44:40.397Z",
            "tags": [],
            "classTitle": "Top",
            "points": {
                "exterior": [
                    [
                        18,
                        26
                    ]
                ],
                "interior": []
            }
        },
        {
            "id": 1037300792,
            "classId": 10374605,
            "description": "",
            "geometryType": "point",
            "labelerLogin": "Peter",
            "createdAt": "2022-09-25T13:44:38.401Z",
            "updatedAt": "2022-09-25T13:44:38.401Z",
            "tags": [],
            "classTitle": "Top",
            "points": {
                "exterior": [
                    [
                        17,
                        38
                    ]
                ],
                "interior": []
            }
        },
        {
            "id": 1037300791,
            "classId": 10374605,
            "description": "",
            "geometryType": "point",
            "labelerLogin": "Peter",
            "createdAt": "2022-09-25T13:44:36.423Z",
            "updatedAt": "2022-09-25T13:44:36.423Z",
            "tags": [],
            "classTitle": "Top",
            "points": {
                "exterior": [
                    [
                        16,
                        51
                    ]
                ],
                "interior": []
            }
        }
    ]
}