{
    "description": "",
    "tags": [],
    "size": {
        "height": 64,
        "width": 48
    },
    "objects": [
        {
            "id": 1037983849,
            "classId": 10374605,
            "description": "",
            "geometryType": "point",
            "labelerLogin": "Peter",
            "createdAt": "2022-09-26T15:21:34.894Z",
            "updatedAt": "2022-09-26T15:21:34.894Z",
            "tags": [],
            "classTitle": "Top",
            "points": {
                "exterior": [
                    [
                        32,
                        50
                    ]
                ],
                "interior": []
            }
        },
        {
            "id": 1037983848,
            "classId": 10374605,
            "description": "",
            "geometryType": "point",
            "labelerLogin": "Peter",
            "createdAt": "2022-09-26T15:21:33.929Z",
            "updatedAt": "2022-09-26T15:21:33.929Z",
            "tags": [],
            "classTitle": "Top",
            "points": {
                "exterior": [
                    [
                        30,
                        34
                    ]
                ],
                "interior": []
            }
        },
        {
            "id": 1037983845,
            "classId": 10374605,
            "description": "",
            "geometryType": "point",
            "labelerLogin": "Peter",
            "createdAt": "2022-09-26T15:21:33.110Z",
            "updatedAt": "2022-09-26T15:21:33.110Z",
            "tags": [],
            "classTitle": "Top",
            "points": {
                "exterior": [
                    [
                        29,
                        22
                    ]
                ],
                "interior": []
            }
        },
        {
            "id": 1037983838,
            "classId": 10374605,
            "description": "",
            "geometryType": "point",
            "labelerLogin": "Peter",
            "createdAt": "2022-09-26T15:21:31.929Z",
            "updatedAt": "2022-09-26T15:21:31.929Z",
            "tags": [],
            "classTitle": "Top",
            "points": {
                "exterior": [
                    [
                        24,
                        7
                    ]
                ],
                "interior": []
            }
        },
        {
            "id": 1037983837,
            "classId": 10374605,
            "description": "",
            "geometryType": "point",
            "labelerLogin": "Peter",
            "createdAt": "2022-09-26T15:21:30.947Z",
            "updatedAt": "2022-09-26T15:21:30.947Z",
            "tags": [],
            "classTitle": "Top",
            "points": {
                "exterior": [
                    [
                        18,
                        22
                    ]
                ],
                "interior": []
            }
        },
        {
            "id": 1037983835,
            "classId": 10374605,
            "description": "",
            "geometryType": "point",
            "labelerLogin": "Peter",
            "createdAt": "2022-09-26T15:21:30.103Z",
            "updatedAt": "2022-09-26T15:21:30.103Z",
            "tags": [],
            "classTitle": "Top",
            "points": {
                "exterior": [
                    [
                        16,
                        34
                    ]
                ],
                "interior": []
            }
        },
        {
            "id": 1037983834,
            "classId": 10374605,
            "description": "",
            "geometryType": "point",
            "labelerLogin": "Peter",
            "createdAt": "2022-09-26T15:21:29.195Z",
            "updatedAt": "2022-09-26T15:21:29.195Z",
            "tags": [],
            "classTitle": "Top",
            "points": {
                "exterior": [
                    [
                        12,
                        51
                    ]
                ],
                "interior": []
            }
        }
    ]
}