{
    "description": "",
    "tags": [],
    "size": {
        "height": 64,
        "width": 48
    },
    "objects": [
        {
            "id": 1037269276,
            "classId": 10374581,
            "description": "",
            "geometryType": "point",
            "labelerLogin": "akoublis",
            "createdAt": "2022-09-24T15:26:34.288Z",
            "updatedAt": "2022-09-24T15:26:41.802Z",
            "tags": [],
            "classTitle": "Top",
            "points": {
                "exterior": [
                    [
                        35,
                        50
                    ]
                ],
                "interior": []
            }
        },
        {
            "id": 1037269275,
            "classId": 10374581,
            "description": "",
            "geometryType": "point",
            "labelerLogin": "akoublis",
            "createdAt": "2022-09-24T15:26:32.347Z",
            "updatedAt": "2022-09-24T15:26:51.377Z",
            "tags": [],
            "classTitle": "Top",
            "points": {
                "exterior": [
                    [
                        30,
                        33
                    ]
                ],
                "interior": []
            }
        },
        {
            "id": 1037269274,
            "classId": 10374581,
            "description": "",
            "geometryType": "point",
            "labelerLogin": "akoublis",
            "createdAt": "2022-09-24T15:26:30.495Z",
            "updatedAt": "2022-09-24T15:26:30.495Z",
            "tags": [],
            "classTitle": "Top",
            "points": {
                "exterior": [
                    [
                        27,
                        19
                    ]
                ],
                "interior": []
            }
        },
        {
            "id": 1037269273,
            "classId": 10374581,
            "description": "",
            "geometryType": "point",
            "labelerLogin": "akoublis",
            "createdAt": "2022-09-24T15:26:29.241Z",
            "updatedAt": "2022-09-24T15:26:29.241Z",
            "tags": [],
            "classTitle": "Top",
            "points": {
                "exterior": [
                    [
                        21,
                        4
                    ]
                ],
                "interior": []
            }
        },
        {
            "id": 1037269272,
            "classId": 10374581,
            "description": "",
            "geometryType": "point",
            "labelerLogin": "akoublis",
            "createdAt": "2022-09-24T15:26:28.013Z",
            "updatedAt": "2022-09-24T15:26:28.013Z",
            "tags": [],
            "classTitle": "Top",
            "points": {
                "exterior": [
                    [
                        16,
                        20
                    ]
                ],
                "interior": []
            }
        },
        {
            "id": 1037269271,
            "classId": 10374581,
            "description": "",
            "geometryType": "point",
            "labelerLogin": "akoublis",
            "createdAt": "2022-09-24T15:26:26.540Z",
            "updatedAt": "2022-09-24T15:26:26.540Z",
            "tags": [],
            "classTitle": "Top",
            "points": {
                "exterior": [
                    [
                        15,
                        35
                    ]
                ],
                "interior": []
            }
        },
        {
            "id": 1037269269,
            "classId": 10374581,
            "description": "",
            "geometryType": "point",
            "labelerLogin": "akoublis",
            "createdAt": "2022-09-24T15:26:24.634Z",
            "updatedAt": "2022-09-24T15:26:24.634Z",
            "tags": [],
            "classTitle": "Top",
            "points": {
                "exterior": [
                    [
                        12,
                        51
                    ]
                ],
                "interior": []
            }
        }
    ]
}