{
    "description": "",
    "tags": [],
    "size": {
        "height": 64,
        "width": 48
    },
    "objects": [
        {
            "id": 1037265831,
            "classId": 10374581,
            "description": "",
            "geometryType": "point",
            "labelerLogin": "akoublis",
            "createdAt": "2022-09-24T13:43:32.843Z",
            "updatedAt": "2022-09-24T13:43:32.843Z",
            "tags": [],
            "classTitle": "Top",
            "points": {
                "exterior": [
                    [
                        37,
                        51
                    ]
                ],
                "interior": []
            }
        },
        {
            "id": 1037265817,
            "classId": 10374581,
            "description": "",
            "geometryType": "point",
            "labelerLogin": "akoublis",
            "createdAt": "2022-09-24T13:42:38.941Z",
            "updatedAt": "2022-09-24T13:43:23.567Z",
            "tags": [],
            "classTitle": "Top",
            "points": {
                "exterior": [
                    [
                        33,
                        34
                    ]
                ],
                "interior": []
            }
        },
        {
            "id": 1037265815,
            "classId": 10374581,
            "description": "",
            "geometryType": "point",
            "labelerLogin": "akoublis",
            "createdAt": "2022-09-24T13:42:37.173Z",
            "updatedAt": "2022-09-24T13:43:09.354Z",
            "tags": [],
            "classTitle": "Top",
            "points": {
                "exterior": [
                    [
                        30,
                        19
                    ]
                ],
                "interior": []
            }
        },
        {
            "id": 1037265814,
            "classId": 10374581,
            "description": "",
            "geometryType": "point",
            "labelerLogin": "akoublis",
            "createdAt": "2022-09-24T13:42:35.769Z",
            "updatedAt": "2022-09-24T13:42:58.621Z",
            "tags": [],
            "classTitle": "Top",
            "points": {
                "exterior": [
                    [
                        23,
                        4
                    ]
                ],
                "interior": []
            }
        },
        {
            "id": 1037265813,
            "classId": 10374581,
            "description": "",
            "geometryType": "point",
            "labelerLogin": "akoublis",
            "createdAt": "2022-09-24T13:42:33.710Z",
            "updatedAt": "2022-09-24T13:42:33.710Z",
            "tags": [],
            "classTitle": "Top",
            "points": {
                "exterior": [
                    [
                        17,
                        20
                    ]
                ],
                "interior": []
            }
        },
        {
            "id": 1037265811,
            "classId": 10374581,
            "description": "",
            "geometryType": "point",
            "labelerLogin": "akoublis",
            "createdAt": "2022-09-24T13:42:30.868Z",
            "updatedAt": "2022-09-24T13:42:30.868Z",
            "tags": [],
            "classTitle": "Top",
            "points": {
                "exterior": [
                    [
                        15,
                        35
                    ]
                ],
                "interior": []
            }
        },
        {
            "id": 1037265805,
            "classId": 10374581,
            "description": "",
            "geometryType": "point",
            "labelerLogin": "akoublis",
            "createdAt": "2022-09-24T13:42:16.753Z",
            "updatedAt": "2022-09-24T13:42:25.017Z",
            "tags": [],
            "classTitle": "Top",
            "points": {
                "exterior": [
                    [
                        12,
                        52
                    ]
                ],
                "interior": []
            }
        }
    ]
}